shiny_multiprocessing/__init__.py
shiny_multiprocessing/shiny_multiprocessing.py
shiny_multiprocessing-0.1.4.dist-info/METADATA
shiny_multiprocessing-0.1.4.dist-info/WHEEL
shiny_multiprocessing-0.1.4.dist-info/RECORD
