Metadata-Version: 2.1
Name: shiny-multiprocessing
Version: 0.1.4
Summary: 
License: WTFPL
Author: Maximilian Töpfer
Author-email: maxtoepfer@mailbox.org
Requires-Python: >=3.8,<4.0
Classifier: License :: Other/Proprietary License
Classifier: Programming Language :: Python :: 3
Classifier: Programming Language :: Python :: 3.8
Classifier: Programming Language :: Python :: 3.9
Classifier: Programming Language :: Python :: 3.10
Classifier: Programming Language :: Python :: 3.11
Requires-Dist: pebble (>=5.0.3,<6.0.0)
